samsift/__init__.py
samsift/increment_version.py
samsift/samsift.py
samsift/samsift_norm_sam.py
samsift/version.py
samsift-0.3.1.dist-info/licenses/LICENSE
samsift-0.3.1.dist-info/METADATA
samsift-0.3.1.dist-info/WHEEL
samsift-0.3.1.dist-info/entry_points.txt
samsift-0.3.1.dist-info/top_level.txt
samsift-0.3.1.dist-info/RECORD
