Metadata-Version: 2.4
Name: samsift
Version: 0.3.1
Summary: Advanced filtering and tagging of SAM/BAM alignments using Python expressions
Home-page: https://github.com/karel-brinda/samsift
Author: Karel Brinda
Author-email: karel.brinda@inria.fr
License: MIT
Keywords: SAM,BAM,sequencing,alignment,filtering,tagging,genomics
Classifier: Development Status :: 5 - Production/Stable
Classifier: Programming Language :: Python :: 3 :: Only
Classifier: Operating System :: Unix
Classifier: Environment :: Console
Classifier: Intended Audience :: Science/Research
Classifier: Topic :: Scientific/Engineering :: Bio-Informatics
Requires-Python: >=3.8
License-File: LICENSE
Requires-Dist: pysam
Dynamic: license-file
